LICENSE
MANIFEST.in
Pipfile
README.rst
check_numpy_scipy.py
environment.yml
multinorm.ipynb
multinorm.py
setup.py
test_multinorm.py
docs/Makefile
docs/analyse.rst
docs/api.rst
docs/changes.rst
docs/conf.py
docs/contribute.rst
docs/create.rst
docs/index.rst
docs/install.rst
docs/make.bat
docs/plot.rst
docs/quickstart.rst
docs/reference.rst
docs/references.txt
docs/theory.rst
multinorm.egg-info/PKG-INFO
multinorm.egg-info/SOURCES.txt
multinorm.egg-info/dependency_links.txt
multinorm.egg-info/requires.txt
multinorm.egg-info/top_level.txt