Metadata-Version: 1.1
Name: multinorm
Version: 0.2
Summary: Multivariate Normal Distributions for Humans
Home-page: https://github.com/cdeil/multinorm/
Author: Christoph Deil
Author-email: Deil.Christoph@gmail.com
License: BSD
Platform: UNKNOWN
Classifier: Intended Audience :: Science/Research
Classifier: License :: OSI Approved :: BSD License
Classifier: Programming Language :: Python :: 3
Classifier: Operating System :: OS Independent
Classifier: Development Status :: 3 - Alpha
